pygatt/__init__.py
pygatt/device.py
pygatt/exceptions.py
pygatt/util.py
pygatt/backends/__init__.py
pygatt/backends/backend.py
pygatt/backends/bgapi/__init__.py
pygatt/backends/bgapi/bgapi.py
pygatt/backends/bgapi/bglib.py
pygatt/backends/bgapi/constants.py
pygatt/backends/bgapi/device.py
pygatt/backends/bgapi/error_codes.py
pygatt/backends/bgapi/exceptions.py
pygatt/backends/bgapi/packets.py
pygatt/backends/bgapi/util.py
pygatt/backends/gatttool/__init__.py
pygatt/backends/gatttool/device.py
pygatt/backends/gatttool/gatttool.py
pygatt-5.0.0.dist-info/LICENSE
pygatt-5.0.0.dist-info/METADATA
pygatt-5.0.0.dist-info/WHEEL
pygatt-5.0.0.dist-info/top_level.txt
pygatt-5.0.0.dist-info/RECORD
