Metadata-Version: 2.1
Name: pygatt
Version: 5.0.0
Summary: Python Bluetooth LE (Low Energy) and GATT Library
Home-page: https://github.com/peplin/pygatt
Author: Chris Peplin <github@rhubarbtech.com>
Author-email: github@rhubarbtech.com
License: Apache 2.0 and MIT
Classifier: Intended Audience :: Developers
Classifier: License :: OSI Approved :: Apache Software License
Classifier: License :: OSI Approved :: MIT License
Classifier: Programming Language :: Python
Classifier: Programming Language :: Python :: 3
License-File: LICENSE
Requires-Dist: pyserial
Requires-Dist: enum-compat
Provides-Extra: gatttool
Requires-Dist: pexpect; extra == "gatttool"
